djazz/__init__.py
djazz/asgi.py
djazz/settings.py
djazz/urls.py
djazz/wsgi.py
djazz_cc-0.1.0rc2.dist-info/LICENSE
djazz_cc-0.1.0rc2.dist-info/WHEEL
djazz_cc-0.1.0rc2.dist-info/METADATA
djazz_cc-0.1.0rc2.dist-info/RECORD
